nanoflow/__init__.py
nanoflow/core/__init__.py
nanoflow/core/engine.py
nanoflow/io/__init__.py
nanoflow/io/loader.py
nanoflow/utils/__init__.py
nanoflow/utils/memory.py
nanoflow_669cca38-0.1.0.dist-info/METADATA
nanoflow_669cca38-0.1.0.dist-info/WHEEL
nanoflow_669cca38-0.1.0.dist-info/top_level.txt
nanoflow_669cca38-0.1.0.dist-info/RECORD
