Metadata-Version: 2.4
Name: nanoflow-669cca38
Version: 0.1.0
Requires-Dist: torch
Requires-Dist: transformers
Requires-Dist: safetensors
Requires-Dist: huggingface_hub
Requires-Dist: psutil
Dynamic: requires-dist
